BFS.py
__init__.py
difference.py
find_ner.py
main.py
ner_plot.py
graph_gen/draw.py
graph_gen/graph_show.py
graph_gen/json_form.py
graph_gen/main_kg.py
graph_gen/main_ner.py
graph_gen/matlab.py
graph_gen/merge_json.py
graph_gen/mergeid.py
graph_gen/news_graph.py
graph_gen/open_pickle.py
graph_gen/plot_id.py
graph_gen/plot_mat.py
graph_gen/test.py
graph_gen/test_draw.py
graph_gen/textrank.py
graph_gen/weight.py
graph_kernel-0.0.1.dist-info/LICENSE
graph_kernel-0.0.1.dist-info/METADATA
graph_kernel-0.0.1.dist-info/WHEEL
graph_kernel-0.0.1.dist-info/top_level.txt
graph_kernel-0.0.1.dist-info/RECORD
