Metadata-Version: 2.1
Name: graph-kernel
Version: 0.0.1
Summary: graph gen from text
Author-email: kernel_loophole <zulqarnain.shahid.iqbal@gmail.com>
Classifier: Programming Language :: Python :: 3
Classifier: License :: OSI Approved :: MIT License
Classifier: Operating System :: OS Independent
Requires-Python: >=3.8
License-File: LICENSE
